TkinterExtras/__init__.py
TkinterExtras/module1.py
tkinterextras-0.4.9.dist-info/licenses/LICENSE
tkinterextras-0.4.9.dist-info/METADATA
tkinterextras-0.4.9.dist-info/WHEEL
tkinterextras-0.4.9.dist-info/top_level.txt
tkinterextras-0.4.9.dist-info/RECORD
