Metadata-Version: 2.4
Name: TkinterExtras
Version: 0.4.9
Summary: Some extra classes and functions for tkinter
Home-page: 
Author: Marcus Collins
Author-email: mjdj27123@gmail.com
Classifier: Programming Language :: Python :: 3
Classifier: License :: OSI Approved :: MIT License
Classifier: Operating System :: OS Independent
Requires-Python: >=3.6
License-File: LICENSE
Dynamic: author
Dynamic: author-email
Dynamic: classifier
Dynamic: description-content-type
Dynamic: license-file
Dynamic: requires-python
Dynamic: summary
